benchnpin/__init__.py
benchnpin/baselines/__init__.py
benchnpin/baselines/base_class.py
benchnpin/baselines/feature_extractors.py
benchnpin/baselines/area_clearing/planning_based/gtsp_config.yaml
benchnpin/baselines/box_delivery/__init__.py
benchnpin/baselines/box_delivery/SAM/__init__.py
benchnpin/baselines/box_delivery/SAM/policy.py
benchnpin/baselines/box_delivery/ppo/__init__.py
benchnpin/baselines/box_delivery/ppo/policy.py
benchnpin/baselines/box_delivery/sac/__init__.py
benchnpin/baselines/box_delivery/sac/policy.py
benchnpin/baselines/ship_ice_nav/__init__.py
benchnpin/baselines/ship_ice_nav/planning_based/__init__.py
benchnpin/baselines/ship_ice_nav/planning_based/policy.py
benchnpin/baselines/ship_ice_nav/planning_based/planners/__init__.py
benchnpin/baselines/ship_ice_nav/planning_based/planners/lattice.py
benchnpin/baselines/ship_ice_nav/planning_based/planners/predictive.py
benchnpin/baselines/ship_ice_nav/planning_based/planners/planner_configs/lattice_config.yaml
benchnpin/baselines/ship_ice_nav/planning_based/planners/planner_configs/predictive_config.yaml
benchnpin/baselines/ship_ice_nav/ppo/__init__.py
benchnpin/baselines/ship_ice_nav/ppo/policy.py
benchnpin/baselines/ship_ice_nav/sac/__init__.py
benchnpin/baselines/ship_ice_nav/sac/policy.py
benchnpin/common/__init__.py
benchnpin/common/cost_map.py
benchnpin/common/cost_map_occ.py
benchnpin/common/path_smoothing.py
benchnpin/common/primitives.py
benchnpin/common/robot.py
benchnpin/common/ship.py
benchnpin/common/swath.py
benchnpin/common/types.py
benchnpin/common/controller/__init__.py
benchnpin/common/controller/dp.py
benchnpin/common/controller/position_controller.py
benchnpin/common/dubins_helpers/__init__.py
benchnpin/common/dubins_helpers/control.py
benchnpin/common/dubins_helpers/heuristic.py
benchnpin/common/evaluation/__init__.py
benchnpin/common/evaluation/metrics.py
benchnpin/common/geometry/__init__.py
benchnpin/common/geometry/polygon.py
benchnpin/common/metrics/__init__.py
benchnpin-0.1.1.dist-info/LICENSE
benchnpin-0.1.1.dist-info/METADATA
benchnpin-0.1.1.dist-info/WHEEL
benchnpin-0.1.1.dist-info/dependency_links.txt
benchnpin-0.1.1.dist-info/top_level.txt
benchnpin-0.1.1.dist-info/RECORD
