Metadata-Version: 2.1
Name: benchnpin
Version: 0.1.1
Summary: Benchmarking Non-prehensile Interactive Navigation
Home-page: https://github.com/IvanIZ/BenchNPIN
License: MIT
Classifier: Programming Language :: Python :: 3.10
Classifier: License :: OSI Approved :: MIT License
Classifier: Operating System :: OS Independent
Requires-Python: >=3.10
License-File: LICENSE
Requires-Dist: numpy
Requires-Dist: matplotlib==3.7.5
Requires-Dist: scikit-image
Requires-Dist: pyyaml
Requires-Dist: tqdm
Requires-Dist: scipy
Requires-Dist: networkx
Requires-Dist: numba
Requires-Dist: shapely
Requires-Dist: pymunk==6.5.1
Requires-Dist: torch
Requires-Dist: torchvision
Requires-Dist: gymnasium
Requires-Dist: stable-baselines3
Requires-Dist: tensorboard
Requires-Dist: pygame
Requires-Dist: opencv-python
Requires-Dist: pynput
